misprint/__init__.py
misprint/py.typed
misprint-0.2.0.dist-info/METADATA
misprint-0.2.0.dist-info/WHEEL
misprint-0.2.0.dist-info/licenses/LICENSE
misprint-0.2.0.dist-info/RECORD
