Metadata-Version: 2.1
Name: misprint
Version: 0.2.0
Summary: A logging filter that 'misprints' your secrets
Project-URL: Documentation, https://github.com/unknown/misprint#readme
Project-URL: Issues, https://github.com/unknown/misprint/issues
Project-URL: Source, https://github.com/unknown/misprint
Author-email: Bernard Cooke <bernard-cooke@hotmail.com>
License-Expression: MIT
License-File: LICENSE
Classifier: Development Status :: 4 - Beta
Classifier: Programming Language :: Python
Classifier: Programming Language :: Python :: 3.8
Classifier: Programming Language :: Python :: 3.9
Classifier: Programming Language :: Python :: 3.10
Classifier: Programming Language :: Python :: 3.11
Classifier: Programming Language :: Python :: 3.12
Classifier: Programming Language :: Python :: Implementation :: CPython
Classifier: Programming Language :: Python :: Implementation :: PyPy
Requires-Python: >=3.8
